gepetuto/__init__.py
gepetuto/__main__.py
gepetuto/generate.py
gepetuto/lint.py
gepetuto/magic.py
gepetuto/main.py
gepetuto/test.py
gepetuto-2.0.3.dist-info/METADATA
gepetuto-2.0.3.dist-info/WHEEL
gepetuto-2.0.3.dist-info/entry_points.txt
gepetuto-2.0.3.dist-info/licenses/LICENSE
gepetuto-2.0.3.dist-info/RECORD
