Metadata-Version: 2.4
Name: gepetuto
Version: 2.0.3
Summary: Tutorial edition framework
Project-URL: changelog, https://github.com/gepetto/gepetuto/blob/main/CHANGELOG.md
Project-URL: homepage, https://github.com/gepetto/gepetuto
Author-email: Guilhem Saurel <guilhem.saurel@laas.fr>, Nicolas Mansard <nmansard@laas.fr>, Théo Martinez <tmartinez@laas.fr>
License-Expression: BSD-2-Clause
License-File: LICENSE
Requires-Python: >=3.10
Requires-Dist: jupyterlab>=4.4.4
Requires-Dist: ruff>=0.12.1
